dropdown/__init__.py
dropdown/apps.py
dropdown/functions.py
dropdown/getter.py
dropdown/helpers.py
dropdown/registry.py
dropdown/serializers.py
dropdown/types.py
dropdown/utils.py
dropdown/views.py
drf_dropdown-0.4.1.dist-info/METADATA
drf_dropdown-0.4.1.dist-info/LICENSE
drf_dropdown-0.4.1.dist-info/WHEEL
drf_dropdown-0.4.1.dist-info/RECORD
