Metadata-Version: 2.1
Name: drf-dropdown
Version: 0.4.1
Summary: Dropdown population implementation for Django REST Framework
Home-page: https://github.com/earthpyy/drf-dropdown
License: MIT
Keywords: django,restframework,drf,dropdown
Author: Preeti Yuankrathok
Author-email: preetisatit@gmail.com
Requires-Python: >=3.8,<4.0
Classifier: License :: OSI Approved :: MIT License
Classifier: Programming Language :: Python :: 3
Classifier: Programming Language :: Python :: 3.8
Classifier: Programming Language :: Python :: 3.9
Classifier: Programming Language :: Python :: 3.10
Classifier: Programming Language :: Python :: 3.11
Requires-Dist: django (>=3.1)
Requires-Dist: djangorestframework (>=3.11.0,<4.0.0)
Project-URL: Repository, https://github.com/earthpyy/drf-dropdown
